infrared_openstack-3.0.0.dist-info/DESCRIPTION.rst
infrared_openstack-3.0.0.dist-info/METADATA
infrared_openstack-3.0.0.dist-info/RECORD
infrared_openstack-3.0.0.dist-info/WHEEL
infrared_openstack-3.0.0.dist-info/entry_points.txt
infrared_openstack-3.0.0.dist-info/metadata.json
infrared_openstack-3.0.0.dist-info/pbr.json
infrared_openstack-3.0.0.dist-info/top_level.txt
openstack/__init__.py
openstack/cleanup.yml
openstack/main.yml
openstack/ovb.yml
openstack/plugin.spec
openstack/post.yml
openstack/pre.yml
openstack/provision.yml
openstack/provision_network_resources.yml
openstack/provision_vms.yml
openstack/defaults/topology/network/3_nets.yml
openstack/defaults/topology/network/3_nets_ovb.yml
openstack/defaults/topology/nodes/aio.yml
openstack/defaults/topology/nodes/bmc.yml
openstack/defaults/topology/nodes/compute.yml
openstack/defaults/topology/nodes/contnet.yml
openstack/defaults/topology/nodes/controller.yml
openstack/defaults/topology/nodes/odl.yml
openstack/defaults/topology/nodes/ovb_ceph.yml
openstack/defaults/topology/nodes/ovb_compute.yml
openstack/defaults/topology/nodes/ovb_controller.yml
openstack/defaults/topology/nodes/ovb_undercloud.yml
openstack/defaults/topology/nodes/tester.yml
openstack/library/os_floating_ip.py
openstack/roles/bmc/files/config-bmc-ips.service
openstack/roles/bmc/tasks/main.yml
openstack/roles/bmc/tasks/openstack-bmc.yml
openstack/roles/bmc/templates/openstack-bmc-service.j2
openstack/roles/bmc/templates/openstackbmc
openstack/roles/bmc/templates/os-net-config.j2
openstack/roles/bmc/vars/main.yml
openstack/roles/hostvars/defaults/main.yml
openstack/roles/hostvars/tasks/cleanup.yml
openstack/roles/hostvars/tasks/main.yml
openstack/roles/hostvars/tasks/save.yml
openstack/roles/hostvars/templates/host_vars.yml.j2
openstack/tasks/cleanup_resources.yml
openstack/tasks/create_network_resources.yml
openstack/tasks/keys.yml
openstack/tasks/register_resources_file.yml
openstack/tasks/servers.yml
openstack/vars/topology/network/README
openstack/vars/topology/nodes/README
